.gitignore
COPYING.LESSER.txt
MANIFEST.in
README.rst
setup.py
score/__init__.py
score.jslib.egg-info/PKG-INFO
score.jslib.egg-info/SOURCES.txt
score.jslib.egg-info/dependency_links.txt
score.jslib.egg-info/entry_points.txt
score.jslib.egg-info/not-zip-safe
score.jslib.egg-info/requires.txt
score.jslib.egg-info/top_level.txt
score/jslib/__init__.py
score/jslib/_init.py
score/jslib/almond.js
score/jslib/cli.py
score/jslib/require.js